aiosqlitedict/__init__.py
aiosqlitedict/database.py
aiosqlitedict-0.0.29.dist-info/LICENSE
aiosqlitedict-0.0.29.dist-info/METADATA
aiosqlitedict-0.0.29.dist-info/WHEEL
aiosqlitedict-0.0.29.dist-info/top_level.txt
aiosqlitedict-0.0.29.dist-info/RECORD
