Metadata-Version: 2.1
Name: aiosqlitedict
Version: 0.0.29
Summary: Aiosqlitedict is a Python Wrapper for Aiosqlite.
Home-page: https://github.com/sabrysm/aiosqlitedict
Author: Abdelrahman Sabry
Author-email: drakth5364@gmail.com
Project-URL: Bug Tracker, https://github.com/sabrysm/aiosqlitedict/issues
Classifier: Programming Language :: Python :: 3
Classifier: License :: OSI Approved :: MIT License
Classifier: Operating System :: OS Independent
Requires-Python: >=3.6
License-File: LICENSE
